crds_generator/__init__.py
crds_generator-0.0.6.dist-info/METADATA
crds_generator-0.0.6.dist-info/WHEEL
crds_generator-0.0.6.dist-info/RECORD
